sqlcsvsql/__init__.py
sqlcsvsql/__main__.py
sqlcsvsql/converters/__init__.py
sqlcsvsql/converters/csv_to_sql.py
sqlcsvsql/converters/sql_to_csv.py
sqlcsvsql/sqlparsers/__init__.py
sqlcsvsql/sqlparsers/parsers.py
sqlcsvsql/sqlparsers/reg_exp.py
sqlcsvsql-0.0.2.dist-info/LICENSE
sqlcsvsql-0.0.2.dist-info/METADATA
sqlcsvsql-0.0.2.dist-info/WHEEL
sqlcsvsql-0.0.2.dist-info/entry_points.txt
sqlcsvsql-0.0.2.dist-info/top_level.txt
sqlcsvsql-0.0.2.dist-info/RECORD
