Metadata-Version: 2.1
Name: sqlcsvsql
Version: 0.0.2
Summary: a lightweight package to convert files between sql and csv
Home-page: https://github.com/riyadhrazzaq/sqlcsvsql
Author: Md. Abdur Razzaq Riyadh
Author-email: riyadh.razzaq@gmail.com
License: UNKNOWN
Project-URL: Bug Tracker, https://github.com/riyadhrazzaq/sqlcsvsql/issues
Platform: UNKNOWN
Classifier: Programming Language :: Python :: 3
Classifier: License :: OSI Approved :: MIT License
Classifier: Operating System :: OS Independent
Requires-Python: >=3.6
License-File: LICENSE
